BazaarWrapper/__init__.py
BazaarWrapper/wrapper.py
BazaarWrapper-0.0.1.dist-info/METADATA
BazaarWrapper-0.0.1.dist-info/WHEEL
BazaarWrapper-0.0.1.dist-info/top_level.txt
BazaarWrapper-0.0.1.dist-info/RECORD
