Metadata-Version: 2.1
Name: BazaarWrapper
Version: 0.0.1
Summary: My personal Wrapper package for Hypixel Skyblock Bazaar
Home-page: https://github.com/Mrmii321/SoapBazaarWrapper
Author: soapchan
Author-email: noahfoxgaming@gmail.com
License: MIT
Requires-Python: >=3.6
Requires-Dist: requests
